hetsar/__init__.py
hetsar/estimators.py
hetsar/utils.py
hetsar/datasets/__init__.py
hetsar/datasets/utils.py
hetsar/datasets/simulated/__init__.py
hetsar/datasets/simulated/data_dynamic1_gaussian0_N025_T200.csv
hetsar/datasets/simulated/weight_matrix_N025.csv
hetsar-5.1.dist-info/LICENSE
hetsar-5.1.dist-info/METADATA
hetsar-5.1.dist-info/WHEEL
hetsar-5.1.dist-info/top_level.txt
hetsar-5.1.dist-info/RECORD
