Metadata-Version: 2.1
Name: hetsar
Version: 5.1
Summary: Estimation of spatial autoregressive panel data models with heterogeneous coefficients
Home-page: https://github.com/ida-j/hetsar
Author: Ida Johnsson
Author-email: ida.b.johnsson@gmail.com
License: UNKNOWN
Platform: UNKNOWN
Classifier: Programming Language :: Python :: 3
Classifier: License :: OSI Approved :: BSD License
Classifier: Operating System :: OS Independent
Requires-Python: >=3.6
License-File: LICENSE
